kafka_async/__init__.py
kafka_async/_admin.py
kafka_async/_consumer.py
kafka_async/_producer.py
kafka_async/_utils.py
kafka_async/_version.py
kafka_async/py.typed
kafka_async-0.0.2.dist-info/licenses/LICENSE
kafka_async-0.0.2.dist-info/METADATA
kafka_async-0.0.2.dist-info/WHEEL
kafka_async-0.0.2.dist-info/top_level.txt
kafka_async-0.0.2.dist-info/RECORD
