Metadata-Version: 2.4
Name: kafka-async
Version: 0.0.2
Summary: Thin async wrapper for Confluent Kafka Python client
Author-email: Timofei Kukushkin <tima@kukushkin.me>
License: MIT License
Project-URL: Homepage, https://github.com/tkukushkin/kafka-async
Project-URL: Repository, https://github.com/tkukushkin/kafka-async.git
Project-URL: Issues, https://github.com/tkukushkin/kafka-async/issues
Project-URL: Documentation, https://kafka-async.readthedocs.io/stable
Project-URL: Changelog, https://github.com/tkukushkin/kafka-async/releases
Classifier: Development Status :: 4 - Beta
Classifier: Intended Audience :: Developers
Classifier: License :: OSI Approved :: MIT License
Classifier: Operating System :: OS Independent
Classifier: Programming Language :: Python :: 3
Classifier: Programming Language :: Python :: 3.10
Classifier: Programming Language :: Python :: 3.11
Classifier: Programming Language :: Python :: 3.12
Classifier: Programming Language :: Python :: 3.13
Classifier: Topic :: Software Development :: Libraries :: Python Modules
Classifier: Framework :: AsyncIO
Classifier: Framework :: Trio
Requires-Python: >=3.10
License-File: LICENSE
Requires-Dist: anyio
Requires-Dist: confluent-kafka>=2.10.0
Requires-Dist: exceptiongroup; python_version < "3.11"
Dynamic: license-file
